cdmn/API.py
cdmn/__init__.py
cdmn/cdmn.py
cdmn/glossary.py
cdmn/idply.py
cdmn/idpname.py
cdmn/interpret.py
cdmn/parse_xml.py
cdmn/parsetab.py
cdmn/post_process.py
cdmn/table.py
cdmn/table_operations.py
cdmn-2.1.2.dist-info/LICENSE
cdmn-2.1.2.dist-info/METADATA
cdmn-2.1.2.dist-info/WHEEL
cdmn-2.1.2.dist-info/entry_points.txt
cdmn-2.1.2.dist-info/top_level.txt
cdmn-2.1.2.dist-info/RECORD
