Metadata-Version: 2.1
Name: cdmn
Version: 2.1.2
Summary: A package providing a (c)DMN solver and API
Home-page: http://cdmn.be
Author: Simon Vandevelde
Author-email: s.vandevelde@kuleuven.be
Requires-Python: >=3.7
License-File: LICENSE
Requires-Dist: openpyxl ==3.0.10
Requires-Dist: ply ==3.11
Requires-Dist: numpy
Requires-Dist: python-dateutil
Requires-Dist: Levenshtein
